universalisapi/__init__.py
universalisapi/_wrapper.py
universalisapi/client.py
universalisapi/exceptions.py
universalisapi/api_objects/__init__.py
universalisapi/api_objects/enums.py
universalisapi/api_objects/listing.py
universalisapi/api_objects/mb_data.py
universalisapi-0.1.1.dist-info/METADATA
universalisapi-0.1.1.dist-info/WHEEL
universalisapi-0.1.1.dist-info/RECORD
