Metadata-Version: 2.4
Name: universalisapi
Version: 0.1.1
Summary: Add your description here
Requires-Python: >=3.13
Requires-Dist: aiohttp>=3.11.11
Requires-Dist: async-property>=0.2.2
